src/core.v
module core(
            input wire        clk,
            input wire        rst,
            input wire        mem_ready,
            input wire [31:0] mem_read_data,
            output reg [31:0] mem_addr = 32'h0,
            output reg        mem_read_valid,
            output reg        mem_write_valid,
            output reg [31:0] mem_write_data = 32'h0,
            output reg [1:0]  mem_width = 2'd0,
            output reg        instruction_retired = 1'b0
);

   // how do we begin?
   // start with an input register for instruction, deal with fetches later when we have memory
   // maybe we can be a little smarter to begin with:
   // - have inputs/outputs for memory reads/writes

   // I don't think I'm going to try to make it pipelined, to begin with

   // MEMORY
   // I'd like to unify fetch and load/stores to one memory interface
   // How does this work with the state machine?
   // - FETCH waits for mem_ready and registers instruction
   // - EXECUTE sets mem_addr/data and mem_valid for ld/st
   // - WRITEBACK waits for mem_ready if ld/st, then sets mem_addr to next pc, mem_valid
   // Should we add a mem_ready signal?
   // Should we implement the memory as an AXI bus?

   // Memory widths for mem_width signal
   localparam MEM_B = 2'd0;
   localparam MEM_H = 2'd1;
   localparam MEM_W = 2'd2;

   // x0-x31 registers
   // note that x0 is always 0, technically could make this size 31
   // - for now rely on the fact that at rst all regs are 0, and x0 is never written
   // other special registers:
   // - x1 = ra = return addr
   // - x2 = sp
   reg [31:0] regfile [0:31];
   reg [31:0] pc = 32'h0;

   // 4 stages (FSM states?):
   // 1. fetch
   //   - set fetch_addr to $pc
   // 2. decode
   //   - should be purely combinatorial, I think
   // 3. execute
   // 4. writeback

   localparam STATE_FETCH = 0;
   localparam STATE_MEM = 1;
   localparam STATE_EXECUTE = 2;
   localparam STATE_WRITEBACK = 3;

   reg [1:0]  state = STATE_FETCH;

   reg [31:0] instr = 32'b0;
   // instruction decoding
   wire [6:0]  opcode = instr[6:0]; // all types
   wire [4:0]  rd = instr[11:7]; // types R, I, U, J
   wire [2:0]  funct3 = instr[14:12]; // types R, I, S, B
   wire [4:0]  rs1 = instr[19:15]; // types R, I, S, B
   wire [4:0]  rs2 = instr[24:20]; // types R, S, B
   wire [6:0]  funct7 = instr[31:25]; // type R

   wire        is_r_type = opcode == 7'b0110011;
   wire        is_i_type = opcode == 7'b0010011 || opcode == 7'b0000011 || opcode == 7'b1100111 || opcode == 7'b1110011;
   wire        is_s_type = opcode == 7'b0100011;
   wire        is_b_type = opcode == 7'b1100011;
   wire        is_u_type = opcode == 7'b0110111 || opcode == 7'b0010111;
   wire        is_j_type = opcode == 7'b1101111;

   wire        is_load   = opcode == 7'b0000011;

   wire        rd_valid = is_r_type || is_i_type || is_u_type || is_j_type;
   wire        is_mem = is_load || is_s_type;


   // R type has no immediate
   // immediate must be sign-extended
   wire [31:0] imm = (is_i_type? {{20{instr[31]}}, instr[31:20]}:
                      is_s_type? {{20{instr[31]}}, instr[31:25], instr[11:7]}:
                      is_b_type? {{20{instr[31]}}, instr[7], instr[30:25], instr[11:8], 1'b0}:
                      is_u_type? {instr[31:12], 12'b0}:
                      is_j_type? {{12{instr[31]}}, instr[19:12], instr[20], instr[30:21]}:
                      32'b0);

   wire        is_add   = is_r_type && funct3 == 3'h0 && funct7 == 7'h00;
   wire        is_sub   = is_r_type && funct3 == 3'h0 && funct7 == 7'h20;
   wire        is_xor   = is_r_type && funct3 == 3'h4 && funct7 == 7'h00;
   wire        is_or    = is_r_type && funct3 == 3'h6 && funct7 == 7'h00;
   wire        is_and   = is_r_type && funct3 == 3'h7 && funct7 == 7'h00;
   wire        is_sll   = is_r_type && funct3 == 3'h1 && funct7 == 7'h00;
   wire        is_srl   = is_r_type && funct3 == 3'h5 && funct7 == 7'h00;
   wire        is_sra   = is_r_type && funct3 == 3'h5 && funct7 == 7'h20;
   wire        is_slt   = is_r_type && funct3 == 3'h2 && funct7 == 7'h00;
   wire        is_sltu  = is_r_type && funct3 == 3'h3 && funct7 == 7'h00;

   // There are multiple categories of I-type instructions, so be explicit with the opcode
   wire        is_addi  = opcode == 7'b0010011 && funct3 == 3'h0;
   wire        is_xori  = opcode == 7'b0010011 && funct3 == 3'h4;
   wire        is_ori   = opcode == 7'b0010011 && funct3 == 3'h6;
   wire        is_andi  = opcode == 7'b0010011 && funct3 == 3'h7;
   wire        is_slli  = opcode == 7'b0010011 && funct3 == 3'h1 && imm[11:5] == 7'h00; // imm[11:5] is funct7
   wire        is_srli  = opcode == 7'b0010011 && funct3 == 3'h5 && imm[11:5] == 7'h00;
   wire        is_srai  = opcode == 7'b0010011 && funct3 == 3'h5 && imm[11:5] == 7'h20;
   wire        is_slti  = opcode == 7'b0010011 && funct3 == 3'h2;
   wire        is_sltiu = opcode == 7'b0010011 && funct3 == 3'h3;

   wire        is_lb    = is_load && funct3 == 3'h0;
   wire        is_lh    = is_load && funct3 == 3'h1;
   wire        is_lw    = is_load && funct3 == 3'h2;
   wire        is_lbu   = is_load && funct3 == 3'h4;
   wire        is_lhu   = is_load && funct3 == 3'h5;

   wire        is_sb    = is_s_type && funct3 == 3'h0;
   wire        is_sh    = is_s_type && funct3 == 3'h1;
   wire        is_sw    = is_s_type && funct3 == 3'h2;

   wire        is_beq   = is_b_type && funct3 == 3'h0;
   wire        is_bne   = is_b_type && funct3 == 3'h1;
   wire        is_blt   = is_b_type && funct3 == 3'h4;
   wire        is_bge   = is_b_type && funct3 == 3'h5;
   wire        is_bltu  = is_b_type && funct3 == 3'h6;
   wire        is_bgeu  = is_b_type && funct3 == 3'h7;

   wire        is_jal   = is_j_type;
   wire        is_jalr  = opcode == 7'b1100111 && funct3 == 3'h0;

   wire        is_lui   = opcode == 7'b0110111;
   wire        is_auipc = opcode == 7'b0010111;

   integer     i;

   // TODO not implemented:
   // - ecall, ebreak
   // - any extensions

   reg [31:0]  result = 32'h0;
   reg         branch_taken = 1'b0;
   wire [31:0] new_pc = (branch_taken? pc + imm:
                        is_jal?       pc + imm:
                        // if rd == rs1 this will still get the old rs1
                        is_jalr?      regfile[rs1] + imm:
                        // default increment pc
                                      pc + 32'd4);

   always @(posedge clk) begin
      // DEFAULT ASSIGNMENTS
      mem_read_valid <= 1'b0;
      mem_write_valid <= 1'b0;
      branch_taken <= 1'b0;
      instruction_retired <= 1'b0;

      if (rst) begin
         pc <= 32'h0;
         // fetch first instruction (32-bit)
         mem_addr <= 32'h0;
         mem_width <= MEM_W;
         state <= STATE_FETCH;
         for (i = 0; i < 32; i = i+1) begin
            regfile[i] <= 32'h0;
         end
         mem_read_valid <= 1'b1;

      end
      else begin
         case (state)
           STATE_FETCH: begin
              // wait for fetched instruction to become available
              if (mem_ready) begin
                 // register the instruction so we can use mem_read_* later
                 instr <= mem_read_data;
                 state <= STATE_EXECUTE;
              end
           end
           STATE_EXECUTE: begin
              // start with arithmetic
              result <= (is_add? regfile[rs1] + regfile[rs2]:
                         is_sub? regfile[rs1] - regfile[rs2]:
                         is_xor? regfile[rs1] ^ regfile[rs2]:
                         is_or?  regfile[rs1] | regfile[rs2]:
                         is_and? regfile[rs1] & regfile[rs2]:
                         is_sll? regfile[rs1] << regfile[rs2]:
                         is_srl? regfile[rs1] >> regfile[rs2]:
                         is_sra? regfile[rs1] >>> regfile[rs2]:
                         is_slt? regfile[rs1] < regfile[rs2]:
                         is_sltu? regfile[rs1] < regfile[rs2]: // TODO

                         is_addi? regfile[rs1] + imm:
                         is_xori? regfile[rs1] ^ imm:
                         is_ori?  regfile[rs1] | imm:
                         is_andi? regfile[rs1] & imm:
                         is_slli? regfile[rs1] << imm:
                         is_srli? regfile[rs1] >> imm:
                         is_srai? regfile[rs1] >>> imm:
                         is_slti? regfile[rs1] < imm:
                         is_sltiu? regfile[rs1] < imm: // TODO
                         is_jal? pc + 4:
                         is_jalr? pc + 4:
                         32'd0);

              branch_taken <= (is_beq?  regfile[rs1] == regfile[rs2]:
                               is_bne?  regfile[rs1] != regfile[rs2]:
                               is_blt?  regfile[rs1] <  regfile[rs2]:
                               is_bge?  regfile[rs1] >= regfile[rs2]:
                               is_bltu? regfile[rs1] <  regfile[rs2]: // TODO
                               is_bgeu? regfile[rs1] >= regfile[rs2]: // TODO
                               1'b0);
              // deal with jal* separately

              // memory loads
              if (is_load) begin
                 mem_addr <= regfile[rs1] + imm;
                 mem_read_valid <= 1'b1;
                 mem_width <= ((is_lb || is_lbu)? MEM_B:
                               (is_lh || is_lhu)? MEM_H:
                               MEM_W);
              end
              // memory stores
              if (is_s_type) begin
                 mem_addr <= regfile[rs1] + imm;
                 mem_write_valid <= 1'b1;
                 mem_width <= (is_sb? MEM_B:
                               is_sh? MEM_H:
                               MEM_W);
                 mem_write_data <= regfile[rs2];
              end

              state <= STATE_WRITEBACK;
           end
           STATE_WRITEBACK: begin
              if (~is_mem || mem_ready) begin
                 // x0 never gets written back
                 if (rd_valid && rd != 0) begin
                    regfile[rd] <= (is_load? mem_read_data : result);
                 end

                 pc <= new_pc;
                 // Set fetch valid here so data will be ready in the next state
                 mem_read_valid <= 1'b1;
                 // mem_read_addr needs to get the same value as next pc
                 // idk if there's a nicer way to do this
                 mem_addr <= new_pc;

                 state = STATE_FETCH;
                 instruction_retired <= 1'b1;
              end // if (~is_mem || mem_ready)
           end // case: STATE_WRITEBACK


         endcase // case (state)
      end

   end


endmodule // core

sim/core_tb.v
`timescale 1ns/1ps;


module core_tb();

   reg clk = 1'b0;
   reg rst = 1'b1;

   reg [31:0] cnt = 32'h0;
   wire       instruction_retired;

   always begin
      clk <= ~clk;
      #10; // IDK
   end

   always @(posedge clk) begin
      cnt <= cnt + 1;
   end;

   wire mem_read_valid;
   wire mem_write_valid;
   reg  mem_ready = 1'b0;

   // Not sure how to pull these over - maybe can access with corei.MEM_B, etc?
   // Memory widths for mem_width signal
   //localparam MEM_B = 2'd0;
   //localparam MEM_H = 2'd1;
   //localparam MEM_W = 2'd2;

   wire [1:0] mem_width;

   wire [31:0] mem_addr;

   reg [31:0] mem_read_data = 32'h0;
   wire [31:0] mem_write_data;

   core corei(
              .clk(clk),
              .rst(rst),
              .mem_read_valid(mem_read_valid),
              .mem_write_valid(mem_write_valid),
              .mem_addr(mem_addr),
              .mem_width(mem_width),
              .mem_read_data(mem_read_data),
              .mem_write_data(mem_write_data),
              .mem_ready(mem_ready),
              .instruction_retired(instruction_retired)
              );

   /*
    // Fibonacci
    // Initialize x1 and x2
    add  x1, x0, x0
    addi x2, x0, 1
    // 10 iterations
    addi x4, x0, 10
loop:
    // temp = x1 + x2
    add  x3, x1, x2
    // x1 = x2
    add  x1, x0, x2
    // x2 = temp
    add  x2, x0, x3
    // x4--
    addi x4, x4, -1
    // branch if x4 not 0
    bne  x4, x0, loop
    // move result to ra
    add x1, x0, x3

    */

   reg [31:0] progmem [0:8];
   // Combinatoric access to memory currently pointed to as convenience
   wire [31:0] mem_rd_sel = progmem[mem_addr >> 2];


   // memory operations
   always @(posedge clk) begin
      // DEFAULT ASSIGNMENT
      mem_ready <= 1'b0;

      if (mem_read_valid) begin
         // TODO handle misalignment
         mem_read_data <= (mem_width == corei.MEM_B? {24'b0, mem_rd_sel[7:0]}:
                           mem_width == corei.MEM_H? {16'b0, mem_rd_sel[15:0]}:
                           mem_rd_sel);
         mem_ready <= 1'b1;
      end
      if (mem_write_valid) begin
         // TODO handle data widths
         progmem[mem_addr >> 2] <= mem_write_data;
         mem_ready <= 1'b1;

      end
   end

   // instruction counter
   reg [31:0] instruction_counter = 32'd0;
   always @(posedge clk) begin
      if (instruction_retired) begin
         instruction_counter = instruction_counter + 1;
      end
   end

   initial begin
      rst <= 1'b1;
      progmem[0] <= 32'h000000b3; // 00: add  x1, x0, x0
      progmem[1] <= 32'h00100113; // 04: addi x2, x0, 1
      progmem[2] <= 32'h00a00213; // 08: addi x4, x0, 10
      progmem[3] <= 32'h002081b3; // 0c: add  x3, x1, x2
      progmem[4] <= 32'h002000b3; // 10: add  x1, x0, x2
      progmem[5] <= 32'h00300133; // 14: add  x2, x0, x3
      progmem[6] <= 32'hfff20213; // 18: addi x4, x4, -1
      progmem[7] <= 32'hfe0218e3; // 1c: bne  x4, x0, -16
      progmem[8] <= 32'h003000b3; // 20: add  x1, x0, x3

      @(posedge clk);
      @(posedge clk);
      @(posedge clk);
      rst <= 1'b0;

      wait (mem_addr == 32'h20);
      //wait (instruction_counter == 32'd20);

      @(posedge clk);
      @(posedge clk);
      $finish;

   end

   integer i;
   initial begin
      $dumpfile("core_tb.vcd");
      $dumpvars(0);
      for (i = 0; i < 32; i = i+1) begin
         $dumpvars(0, corei.regfile[i]);
      end

   end

endmodule // core_tb

core_tb.vcd
$date
	Thu Aug 28 22:42:17 2025
$end
$version
	Icarus Verilog
$end
$timescale
	1ps
$end
$scope module core_tb $end
$var wire 32 ! mem_rd_sel [31:0] $end
$var wire 1 " mem_write_valid $end
$var wire 32 # mem_write_data [31:0] $end
$var wire 2 $ mem_width [1:0] $end
$var wire 1 % mem_read_valid $end
$var wire 32 & mem_addr [31:0] $end
$var wire 1 ' instruction_retired $end
$var reg 1 ( clk $end
$var reg 32 ) cnt [31:0] $end
$var reg 32 * instruction_counter [31:0] $end
$var reg 32 + mem_read_data [31:0] $end
$var reg 1 , mem_ready $end
$var reg 1 - rst $end
$var integer 32 . i [31:0] $end
$scope module corei $end
$var wire 1 ( clk $end
$var wire 1 / is_add $end
$var wire 1 0 is_addi $end
$var wire 1 1 is_and $end
$var wire 1 2 is_andi $end
$var wire 1 3 is_beq $end
$var wire 1 4 is_bge $end
$var wire 1 5 is_bgeu $end
$var wire 1 6 is_blt $end
$var wire 1 7 is_bltu $end
$var wire 1 8 is_bne $end
$var wire 1 9 is_i_type $end
$var wire 1 : is_jal $end
$var wire 1 ; is_jalr $end
$var wire 1 < is_lb $end
$var wire 1 = is_lbu $end
$var wire 1 > is_lh $end
$var wire 1 ? is_lhu $end
$var wire 1 @ is_lw $end
$var wire 1 A is_mem $end
$var wire 1 B is_or $end
$var wire 1 C is_ori $end
$var wire 1 D is_sb $end
$var wire 1 E is_sh $end
$var wire 1 F is_sll $end
$var wire 1 G is_slli $end
$var wire 1 H is_slt $end
$var wire 1 I is_slti $end
$var wire 1 J is_sltiu $end
$var wire 1 K is_sltu $end
$var wire 1 L is_sra $end
$var wire 1 M is_srai $end
$var wire 1 N is_srl $end
$var wire 1 O is_srli $end
$var wire 1 P is_sub $end
$var wire 1 Q is_sw $end
$var wire 1 R is_u_type $end
$var wire 1 S is_xor $end
$var wire 1 T is_xori $end
$var wire 32 U mem_read_data [31:0] $end
$var wire 1 , mem_ready $end
$var wire 1 V rd_valid $end
$var wire 1 - rst $end
$var wire 5 W rs2 [4:0] $end
$var wire 5 X rs1 [4:0] $end
$var wire 5 Y rd [4:0] $end
$var wire 7 Z opcode [6:0] $end
$var wire 32 [ new_pc [31:0] $end
$var wire 1 \ is_s_type $end
$var wire 1 ] is_r_type $end
$var wire 1 ^ is_lui $end
$var wire 1 _ is_load $end
$var wire 1 ` is_j_type $end
$var wire 1 a is_b_type $end
$var wire 1 b is_auipc $end
$var wire 32 c imm [31:0] $end
$var wire 7 d funct7 [6:0] $end
$var wire 3 e funct3 [2:0] $end
$var parameter 2 f MEM_B $end
$var parameter 2 g MEM_H $end
$var parameter 2 h MEM_W $end
$var parameter 32 i STATE_EXECUTE $end
$var parameter 32 j STATE_FETCH $end
$var parameter 32 k STATE_MEM $end
$var parameter 32 l STATE_WRITEBACK $end
$var reg 1 m branch_taken $end
$var reg 32 n instr [31:0] $end
$var reg 1 ' instruction_retired $end
$var reg 32 o mem_addr [31:0] $end
$var reg 1 % mem_read_valid $end
$var reg 2 p mem_width [1:0] $end
$var reg 32 q mem_write_data [31:0] $end
$var reg 1 " mem_write_valid $end
$var reg 32 r pc [31:0] $end
$var reg 32 s result [31:0] $end
$var reg 2 t state [1:0] $end
$var integer 32 u i [31:0] $end
$upscope $end
$upscope $end
$scope module core_tb $end
$scope module corei $end
$var reg 32 v \regfile[0] [31:0] $end
$upscope $end
$upscope $end
$scope module core_tb $end
$scope module corei $end
$var reg 32 w \regfile[1] [31:0] $end
$upscope $end
$upscope $end
$scope module core_tb $end
$scope module corei $end
$var reg 32 x \regfile[2] [31:0] $end
$upscope $end
$upscope $end
$scope module core_tb $end
$scope module corei $end
$var reg 32 y \regfile[3] [31:0] $end
$upscope $end
$upscope $end
$scope module core_tb $end
$scope module corei $end
$var reg 32 z \regfile[4] [31:0] $end
$upscope $end
$upscope $end
$scope module core_tb $end
$scope module corei $end
$var reg 32 { \regfile[5] [31:0] $end
$upscope $end
$upscope $end
$scope module core_tb $end
$scope module corei $end
$var reg 32 | \regfile[6] [31:0] $end
$upscope $end
$upscope $end
$scope module core_tb $end
$scope module corei $end
$var reg 32 } \regfile[7] [31:0] $end
$upscope $end
$upscope $end
$scope module core_tb $end
$scope module corei $end
$var reg 32 ~ \regfile[8] [31:0] $end
$upscope $end
$upscope $end
$scope module core_tb $end
$scope module corei $end
$var reg 32 !" \regfile[9] [31:0] $end
$upscope $end
$upscope $end
$scope module core_tb $end
$scope module corei $end
$var reg 32 "" \regfile[10] [31:0] $end
$upscope $end
$upscope $end
$scope module core_tb $end
$scope module corei $end
$var reg 32 #" \regfile[11] [31:0] $end
$upscope $end
$upscope $end
$scope module core_tb $end
$scope module corei $end
$var reg 32 $" \regfile[12] [31:0] $end
$upscope $end
$upscope $end
$scope module core_tb $end
$scope module corei $end
$var reg 32 %" \regfile[13] [31:0] $end
$upscope $end
$upscope $end
$scope module core_tb $end
$scope module corei $end
$var reg 32 &" \regfile[14] [31:0] $end
$upscope $end
$upscope $end
$scope module core_tb $end
$scope module corei $end
$var reg 32 '" \regfile[15] [31:0] $end
$upscope $end
$upscope $end
$scope module core_tb $end
$scope module corei $end
$var reg 32 (" \regfile[16] [31:0] $end
$upscope $end
$upscope $end
$scope module core_tb $end
$scope module corei $end
$var reg 32 )" \regfile[17] [31:0] $end
$upscope $end
$upscope $end
$scope module core_tb $end
$scope module corei $end
$var reg 32 *" \regfile[18] [31:0] $end
$upscope $end
$upscope $end
$scope module core_tb $end
$scope module corei $end
$var reg 32 +" \regfile[19] [31:0] $end
$upscope $end
$upscope $end
$scope module core_tb $end
$scope module corei $end
$var reg 32 ," \regfile[20] [31:0] $end
$upscope $end
$upscope $end
$scope module core_tb $end
$scope module corei $end
$var reg 32 -" \regfile[21] [31:0] $end
$upscope $end
$upscope $end
$scope module core_tb $end
$scope module corei $end
$var reg 32 ." \regfile[22] [31:0] $end
$upscope $end
$upscope $end
$scope module core_tb $end
$scope module corei $end
$var reg 32 /" \regfile[23] [31:0] $end
$upscope $end
$upscope $end
$scope module core_tb $end
$scope module corei $end
$var reg 32 0" \regfile[24] [31:0] $end
$upscope $end
$upscope $end
$scope module core_tb $end
$scope module corei $end
$var reg 32 1" \regfile[25] [31:0] $end
$upscope $end
$upscope $end
$scope module core_tb $end
$scope module corei $end
$var reg 32 2" \regfile[26] [31:0] $end
$upscope $end
$upscope $end
$scope module core_tb $end
$scope module corei $end
$var reg 32 3" \regfile[27] [31:0] $end
$upscope $end
$upscope $end
$scope module core_tb $end
$scope module corei $end
$var reg 32 4" \regfile[28] [31:0] $end
$upscope $end
$upscope $end
$scope module core_tb $end
$scope module corei $end
$var reg 32 5" \regfile[29] [31:0] $end
$upscope $end
$upscope $end
$scope module core_tb $end
$scope module corei $end
$var reg 32 6" \regfile[30] [31:0] $end
$upscope $end
$upscope $end
$scope module core_tb $end
$scope module corei $end
$var reg 32 7" \regfile[31] [31:0] $end
$upscope $end
$upscope $end
$enddefinitions $end
$comment Show the parameter values. $end
$dumpall
b11 l
b1 k
b0 j
b10 i
b10 h
b1 g
b0 f
$end
#0
$dumpvars
b0 7"
b0 6"
b0 5"
b0 4"
b0 3"
b0 2"
b0 1"
b0 0"
b0 /"
b0 ."
b0 -"
b0 ,"
b0 +"
b0 *"
b0 )"
b0 ("
b0 '"
b0 &"
b0 %"
b0 $"
b0 #"
b0 ""
b0 !"
b0 ~
b0 }
b0 |
b0 {
b0 z
b0 y
b0 x
b0 w
b0 v
b100000 u
b0 t
b0 s
b0 r
b0 q
b10 p
b0 o
b0 n
0m
b0 e
b0 d
b0 c
0b
0a
0`
0_
0^
0]
0\
b100 [
b0 Z
b0 Y
b0 X
b0 W
0V
b0 U
0T
0S
0R
0Q
0P
0O
0N
0M
0L
0K
0J
0I
0H
0G
0F
0E
0D
0C
0B
0A
0@
0?
0>
0=
0<
0;
0:
09
08
07
06
05
04
03
02
01
00
0/
b100000 .
1-
0,
b0 +
b0 *
b1 )
1(
0'
b0 &
1%
b10 $
b0 #
0"
b10110011 !
$end
#10000
0(
#20000
1,
b10110011 +
b10110011 U
b10 )
b0 7"
b0 6"
b0 5"
b0 4"
b0 3"
b0 2"
b0 1"
b0 0"
b0 /"
b0 ."
b0 -"
b0 ,"
b0 +"
b0 *"
b0 )"
b0 ("
b0 '"
b0 &"
b0 %"
b0 $"
b0 #"
b0 ""
b0 !"
b0 ~
b0 }
b0 |
b0 {
b0 z
b0 y
b0 x
b0 w
b0 v
1%
b100000 u
1(
#30000
0(
#40000
b0 7"
b0 6"
b0 5"
b0 4"
b0 3"
b0 2"
b0 1"
b0 0"
b0 /"
b0 ."
b0 -"
b0 ,"
b0 +"
b0 *"
b0 )"
b0 ("
b0 '"
b0 &"
b0 %"
b0 $"
b0 #"
b0 ""
b0 !"
b0 ~
b0 }
b0 |
b0 {
b0 z
b0 y
b0 x
b0 w
b0 v
1%
b11 )
1,
0-
b100000 u
1(
#50000
0(
#60000
1V
1/
1]
b110011 Z
b1 Y
1,
b100 )
b10 t
b10110011 n
0%
1(
#70000
0(
#80000
b11 t
b101 )
0,
1(
#90000
0(
#100000
b1000 [
b100000000000100010011 !
b110 )
1'
b100 &
b100 o
1%
b100 r
b0 w
b0 t
1(
#110000
0(
#120000
0'
0%
b111 )
1,
b100000000000100010011 +
b100000000000100010011 U
b1 *
1(
#130000
0(
#140000
b1 c
1V
19
0/
10
0]
b10011 Z
b10 Y
b1 W
0,
b1000 )
b10 t
b100000000000100010011 n
1(
#150000
0(
#160000
b11 t
b1 s
b1001 )
1(
#170000
0(
#180000
b1100 [
b101000000000001000010011 !
b1010 )
1'
b1000 &
b1000 o
1%
b1000 r
b1 x
b0 t
1(
#190000
0(
#200000
0'
0%
b1011 )
1,
b101000000000001000010011 +
b101000000000001000010011 U
b10 *
1(
#210000
0(
#220000
b1010 c
b100 Y
b1010 W
0,
b1100 )
b10 t
b101000000000001000010011 n
1(
#230000
0(
#240000
b11 t
b1010 s
b1101 )
1(
#250000
0(
#260000
b10000 [
b1000001000000110110011 !
b1110 )
1'
b1100 &
b1100 o
1%
b1100 r
b1010 z
b0 t
1(
#270000
0(
#280000
0'
0%
b1111 )
1,
b1000001000000110110011 +
b1000001000000110110011 U
b11 *
1(
#290000
0(
#300000
09
1/
00
b0 c
1]
b110011 Z
b11 Y
b1 X
b10 W
0,
b10000 )
b10 t
b1000001000000110110011 n
1(
#310000
0(
#320000
b11 t
b1 s
b10001 )
1(
#330000
0(
#340000
b10100 [
b1000000000000010110011 !
b10010 )
1'
b10000 &
b10000 o
1%
b10000 r
b1 y
b0 t
1(
#350000
0(
#360000
0'
0%
b10011 )
1,
b1000000000000010110011 +
b1000000000000010110011 U
b100 *
1(
#370000
0(
#380000
b1 Y
b0 X
0,
b10100 )
b10 t
b1000000000000010110011 n
1(
#390000
0(
#400000
b11 t
b10101 )
1(
#410000
0(
#420000
b11000 [
b1100000000000100110011 !
b10110 )
1'
b10100 &
b10100 o
1%
b10100 r
b1 w
b0 t
1(
#430000
0(
#440000
0'
0%
b10111 )
1,
b1100000000000100110011 +
b1100000000000100110011 U
b101 *
1(
#450000
0(
#460000
b10 Y
b11 W
0,
b11000 )
b10 t
b1100000000000100110011 n
1(
#470000
0(
#480000
b11 t
b11001 )
1(
#490000
0(
#500000
b11100 [
b11111111111100100000001000010011 !
b11010 )
1'
b11000 &
b11000 o
1%
b11000 r
b1 x
b0 t
1(
#510000
0(
#520000
0'
0%
b11011 )
1,
b11111111111100100000001000010011 +
b11111111111100100000001000010011 U
b110 *
1(
#530000
0(
#540000
b11111111111111111111111111111111 c
1V
19
10
0/
0]
b10011 Z
b100 Y
b100 X
b11111 W
b1111111 d
0,
b11100 )
b10 t
b11111111111100100000001000010011 n
1(
#550000
0(
#560000
b11 t
b1001 s
b11101 )
1(
#570000
0(
#580000
b100000 [
b11111110000000100001100011100011 !
b11110 )
1'
b11100 &
b11100 o
1%
b11100 r
b1001 z
b0 t
1(
#590000
0(
#600000
0'
0%
b11111 )
1,
b11111110000000100001100011100011 +
b11111110000000100001100011100011 U
b111 *
1(
#610000
0(
#620000
0V
09
00
18
b11111111111111111111111111110000 c
1a
b1100011 Z
b10001 Y
b1 e
b0 W
0,
b100000 )
b10 t
b11111110000000100001100011100011 n
1(
#630000
0(
#640000
b1100 [
b11 t
1m
b0 s
b100001 )
1(
#650000
0(
#660000
b1000001000000110110011 !
b10000 [
b100010 )
1'
b1100 &
b1100 o
1%
b1100 r
0m
b0 t
1(
#670000
0(
#680000
0'
0%
b100011 )
1,
b1000001000000110110011 +
b1000001000000110110011 U
b1000 *
1(
#690000
0(
#700000
1V
b0 c
1/
08
1]
0a
b110011 Z
b11 Y
b0 e
b1 X
b10 W
b0 d
0,
b100100 )
b10 t
b1000001000000110110011 n
1(
#710000
0(
#720000
b11 t
b10 s
b100101 )
1(
#730000
0(
#740000
b10100 [
b1000000000000010110011 !
b100110 )
1'
b10000 &
b10000 o
1%
b10000 r
b10 y
b0 t
1(
#750000
0(
#760000
0'
0%
b100111 )
1,
b1000000000000010110011 +
b1000000000000010110011 U
b1001 *
1(
#770000
0(
#780000
b1 Y
b0 X
0,
b101000 )
b10 t
b1000000000000010110011 n
1(
#790000
0(
#800000
b11 t
b1 s
b101001 )
1(
#810000
0(
#820000
b11000 [
b1100000000000100110011 !
b101010 )
1'
b10100 &
b10100 o
1%
b10100 r
b1 w
b0 t
1(
#830000
0(
#840000
0'
0%
b101011 )
1,
b1100000000000100110011 +
b1100000000000100110011 U
b1010 *
1(
#850000
0(
#860000
b10 Y
b11 W
0,
b101100 )
b10 t
b1100000000000100110011 n
1(
#870000
0(
#880000
b11 t
b10 s
b101101 )
1(
#890000
0(
#900000
b11100 [
b11111111111100100000001000010011 !
b101110 )
1'
b11000 &
b11000 o
1%
b11000 r
b10 x
b0 t
1(
#910000
0(
#920000
0'
0%
b101111 )
1,
b11111111111100100000001000010011 +
b11111111111100100000001000010011 U
b1011 *
1(
#930000
0(
#940000
b11111111111111111111111111111111 c
1V
19
10
0/
0]
b10011 Z
b100 Y
b100 X
b11111 W
b1111111 d
0,
b110000 )
b10 t
b11111111111100100000001000010011 n
1(
#950000
0(
#960000
b11 t
b1000 s
b110001 )
1(
#970000
0(
#980000
b100000 [
b11111110000000100001100011100011 !
b110010 )
1'
b11100 &
b11100 o
1%
b11100 r
b1000 z
b0 t
1(
#990000
0(
#1000000
0'
0%
b110011 )
1,
b11111110000000100001100011100011 +
b11111110000000100001100011100011 U
b1100 *
1(
#1010000
0(
#1020000
0V
09
00
18
b11111111111111111111111111110000 c
1a
b1100011 Z
b10001 Y
b1 e
b0 W
0,
b110100 )
b10 t
b11111110000000100001100011100011 n
1(
#1030000
0(
#1040000
b1100 [
b11 t
1m
b0 s
b110101 )
1(
#1050000
0(
#1060000
b1000001000000110110011 !
b10000 [
b110110 )
1'
b1100 &
b1100 o
1%
b1100 r
0m
b0 t
1(
#1070000
0(
#1080000
0'
0%
b110111 )
1,
b1000001000000110110011 +
b1000001000000110110011 U
b1101 *
1(
#1090000
0(
#1100000
1V
b0 c
1/
08
1]
0a
b110011 Z
b11 Y
b0 e
b1 X
b10 W
b0 d
0,
b111000 )
b10 t
b1000001000000110110011 n
1(
#1110000
0(
#1120000
b11 t
b11 s
b111001 )
1(
#1130000
0(
#1140000
b10100 [
b1000000000000010110011 !
b111010 )
1'
b10000 &
b10000 o
1%
b10000 r
b11 y
b0 t
1(
#1150000
0(
#1160000
0'
0%
b111011 )
1,
b1000000000000010110011 +
b1000000000000010110011 U
b1110 *
1(
#1170000
0(
#1180000
b1 Y
b0 X
0,
b111100 )
b10 t
b1000000000000010110011 n
1(
#1190000
0(
#1200000
b11 t
b10 s
b111101 )
1(
#1210000
0(
#1220000
b11000 [
b1100000000000100110011 !
b111110 )
1'
b10100 &
b10100 o
1%
b10100 r
b10 w
b0 t
1(
#1230000
0(
#1240000
0'
0%
b111111 )
1,
b1100000000000100110011 +
b1100000000000100110011 U
b1111 *
1(
#1250000
0(
#1260000
b10 Y
b11 W
0,
b1000000 )
b10 t
b1100000000000100110011 n
1(
#1270000
0(
#1280000
b11 t
b11 s
b1000001 )
1(
#1290000
0(
#1300000
b11100 [
b11111111111100100000001000010011 !
b1000010 )
1'
b11000 &
b11000 o
1%
b11000 r
b11 x
b0 t
1(
#1310000
0(
#1320000
0'
0%
b1000011 )
1,
b11111111111100100000001000010011 +
b11111111111100100000001000010011 U
b10000 *
1(
#1330000
0(
#1340000
b11111111111111111111111111111111 c
1V
19
10
0/
0]
b10011 Z
b100 Y
b100 X
b11111 W
b1111111 d
0,
b1000100 )
b10 t
b11111111111100100000001000010011 n
1(
#1350000
0(
#1360000
b11 t
b111 s
b1000101 )
1(
#1370000
0(
#1380000
b100000 [
b11111110000000100001100011100011 !
b1000110 )
1'
b11100 &
b11100 o
1%
b11100 r
b111 z
b0 t
1(
#1390000
0(
#1400000
0'
0%
b1000111 )
1,
b11111110000000100001100011100011 +
b11111110000000100001100011100011 U
b10001 *
1(
#1410000
0(
#1420000
0V
09
00
18
b11111111111111111111111111110000 c
1a
b1100011 Z
b10001 Y
b1 e
b0 W
0,
b1001000 )
b10 t
b11111110000000100001100011100011 n
1(
#1430000
0(
#1440000
b1100 [
b11 t
1m
b0 s
b1001001 )
1(
